README.md
setup.py
speed.py
speedziweifan.egg-info/PKG-INFO
speedziweifan.egg-info/SOURCES.txt
speedziweifan.egg-info/dependency_links.txt
speedziweifan.egg-info/top_level.txt