Metadata-Version: 2.1
Name: speedziweifan
Version: 1.1.0
Summary: A small example package
Home-page: https://github.com/pypa/example-project
Author: Ziwei Fang
Author-email: 953352945@qq.com
License: UNKNOWN
Platform: UNKNOWN
Classifier: Programming Language :: Python :: 3
Classifier: License :: OSI Approved :: MIT License
Classifier: Operating System :: OS Independent
